yes_no_words.py
yes_no_words-2022.4.8.dist-info/LICENSE
yes_no_words-2022.4.8.dist-info/METADATA
yes_no_words-2022.4.8.dist-info/WHEEL
yes_no_words-2022.4.8.dist-info/top_level.txt
yes_no_words-2022.4.8.dist-info/RECORD
