Metadata-Version: 2.1
Name: yes-no-words
Version: 2022.4.8
Summary: Get yes/no-like words.
Home-page: https://github.com/jefftriplett/yes-no-words
Author: Jeff Triplett
Author-email: jeff.triplett@gmail.com
License: Apache License 2.0
Project-URL: Twitter, https://twitter.com/webology
Keywords: yes no truthy falsy
Platform: UNKNOWN
Classifier: Development Status :: 5 - Production/Stable
Classifier: Intended Audience :: Developers
Classifier: License :: OSI Approved :: MIT License
Classifier: Natural Language :: English
Classifier: Operating System :: OS Independent
Classifier: Programming Language :: Python :: 3 :: Only
Classifier: Programming Language :: Python :: 3
Classifier: Programming Language :: Python :: 3.7
Classifier: Programming Language :: Python :: 3.8
Classifier: Programming Language :: Python :: 3.9
Classifier: Programming Language :: Python :: 3.10
Classifier: Programming Language :: Python :: 3.11
Requires-Python: >=3.7
License-File: LICENSE
